johnsonthy/__init__.pyc
johnsonthy/config/logging.json
johnsonthy/helper/__init__.pyc
johnsonthy/helper/__init__.pyi
johnsonthy/helper/devices.pyc
johnsonthy/helper/devices.pyi
johnsonthy/helper/files.pyc
johnsonthy/helper/files.pyi
johnsonthy/helper/paths.pyc
johnsonthy/helper/paths.pyi
johnsonthy/helper/singletons.pyc
johnsonthy/helper/singletons.pyi
johnsonthy/helper/strings.pyc
johnsonthy/helper/strings.pyi
johnsonthy/helper/times.pyc
johnsonthy/helper/times.pyi
johnsonthy/logging/__init__.pyc
johnsonthy/logging/__init__.pyi
johnsonthy/logging/logger.pyc
johnsonthy/logging/logger.pyi
johnsonthy/message/__init__.pyc
johnsonthy/message/__init__.pyi
johnsonthy/message/event.pyc
johnsonthy/message/event.pyi
johnsonthy/socket/__init__.pyc
johnsonthy/socket/__init__.pyi
johnsonthy/socket/receiver.pyc
johnsonthy/socket/receiver.pyi
johnsonthy/socket/sender.pyc
johnsonthy/socket/sender.pyi
johnsonthy/socket/servers.pyc
johnsonthy/socket/servers.pyi
johnsonthy/thread/__init__.pyc
johnsonthy/thread/__init__.pyi
johnsonthy/thread/handler.pyc
johnsonthy/thread/handler.pyi
johnsonthy-1.2.3.dist-info/METADATA
johnsonthy-1.2.3.dist-info/WHEEL
johnsonthy-1.2.3.dist-info/top_level.txt
johnsonthy-1.2.3.dist-info/RECORD
