Metadata-Version: 2.1
Name: johnsonthy
Version: 1.2.3
Summary: johnson utils
Author: johnson
Classifier: Development Status :: 5 - Production/Stable
Classifier: Intended Audience :: Developers
Classifier: Programming Language :: Python :: 3.9
Classifier: Programming Language :: Python :: 3.10
Classifier: Programming Language :: Python :: 3.11
Classifier: Programming Language :: Python :: 3.12
Classifier: Operating System :: OS Independent
Classifier: License :: OSI Approved :: Apache Software License
Classifier: Topic :: Utilities
